pytest_f3ts/__init__.py
pytest_f3ts/fixtures.py
pytest_f3ts/plugin.py
pytest_f3ts/runner_client.py
pytest_f3ts/schemas/__init__.py
pytest_f3ts/schemas/attachment.py
pytest_f3ts/schemas/case.py
pytest_f3ts/schemas/commit.py
pytest_f3ts/schemas/config.py
pytest_f3ts/schemas/fileutils.py
pytest_f3ts/schemas/limits.py
pytest_f3ts/schemas/msg.py
pytest_f3ts/schemas/plan.py
pytest_f3ts/schemas/result.py
pytest_f3ts/schemas/run.py
pytest_f3ts/schemas/token.py
pytest_f3ts/schemas/user.py
pytest_f3ts/utils.py
pytest_f3ts-1.1.1.dist-info/METADATA
pytest_f3ts-1.1.1.dist-info/WHEEL
pytest_f3ts-1.1.1.dist-info/entry_points.txt
pytest_f3ts-1.1.1.dist-info/licenses/LICENSE
pytest_f3ts-1.1.1.dist-info/RECORD
