Metadata-Version: 2.4
Name: pytest-f3ts
Version: 1.1.1
Summary: Pytest Plugin for communicating test results and information to a FixturFab Test Runner GUI
License-File: LICENSE
Author: Duncan Lowder
Author-email: duncan@fixturfab.com
Requires-Python: >=3.10,<4.0
Classifier: Programming Language :: Python :: 3
Classifier: Programming Language :: Python :: 3.10
Classifier: Programming Language :: Python :: 3.11
Classifier: Programming Language :: Python :: 3.12
Classifier: Programming Language :: Python :: 3.13
Classifier: Programming Language :: Python :: 3.14
Requires-Dist: fastapi (>=0.128.0,<0.129.0)
Requires-Dist: pydantic[email] (>=2.0.0,<3.0.0)
Requires-Dist: pytest (>=7.2.1,<8.0.0)
Requires-Dist: pytest-html (>=4.1.1,<5.0.0)
Requires-Dist: pytest-reportlog (>=0.4.0,<0.5.0)
Requires-Dist: pyyaml (>=6.0,<7.0)
Requires-Dist: requests (>=2.31.0,<3.0.0)
Requires-Dist: sqlalchemy-file (>=0.5.0,<0.6.0)
Requires-Dist: tenacity (>=8.2.3,<9.0.0)
Requires-Dist: toml (>=0.10.2,<0.11.0)
Requires-Dist: websocket-client (>=1.6.2,<2.0.0)
Requires-Dist: websockets (>=11.0.3,<12.0.0)
